config/settings.json
termivox/__init__.py
termivox/cli.py
termivox/download_model.py
termivox/init_wizard.py
termivox/main.py
termivox/test_voice_script.py
termivox/ai/__init__.py
termivox/ai/ai_service.py
termivox/bridge/__init__.py
termivox/bridge/xdotool_bridge.py
termivox/ui/__init__.py
termivox/ui/config_loader.py
termivox/ui/hardware_interface.py
termivox/ui/hotkey_interface.py
termivox/ui/toggle_controller.py
termivox/ui/tray_interface.py
termivox/ui/widget_interface.py
termivox/utils/__init__.py
termivox/voice/__init__.py
termivox/voice/recognizer.py
termivox-0.1.3.dist-info/licenses/LICENSE
termivox-0.1.3.dist-info/METADATA
termivox-0.1.3.dist-info/WHEEL
termivox-0.1.3.dist-info/entry_points.txt
termivox-0.1.3.dist-info/top_level.txt
termivox-0.1.3.dist-info/RECORD
