Metadata-Version: 2.4
Name: termivox
Version: 0.1.3
Summary: Voice Recognition Bridge for Linux - Speak naturally, control your system, type hands-free
Home-page: https://github.com/Gerico1007/termivox
Author: Gerico
Author-email: Gerico <gerico@jgwill.com>
License: MIT
Project-URL: Homepage, https://github.com/Gerico1007/termivox
Project-URL: Repository, https://github.com/Gerico1007/termivox
Project-URL: Issues, https://github.com/Gerico1007/termivox/issues
Keywords: voice-recognition,speech-to-text,linux,vosk,accessibility,hands-free,dictation
Classifier: Development Status :: 4 - Beta
Classifier: Intended Audience :: End Users/Desktop
Classifier: Intended Audience :: Developers
Classifier: Topic :: Multimedia :: Sound/Audio :: Speech
Classifier: Topic :: Desktop Environment
Classifier: Topic :: Adaptive Technologies
Classifier: License :: OSI Approved :: MIT License
Classifier: Programming Language :: Python :: 3
Classifier: Programming Language :: Python :: 3.8
Classifier: Programming Language :: Python :: 3.9
Classifier: Programming Language :: Python :: 3.10
Classifier: Programming Language :: Python :: 3.11
Classifier: Programming Language :: Python :: 3.12
Classifier: Operating System :: POSIX :: Linux
Requires-Python: >=3.8
License-File: LICENSE
Requires-Dist: vosk>=0.3.45
Requires-Dist: pyaudio>=0.2.13
Requires-Dist: numpy>=1.24.0
Requires-Dist: pynput>=1.7.6
Requires-Dist: pystray>=0.19.5
Requires-Dist: Pillow>=10.0.0
Requires-Dist: speechrecognition>=3.10.0
Requires-Dist: python-dotenv>=1.0.0
Requires-Dist: google-generativeai>=0.3.0
Requires-Dist: openai>=1.0.0
Provides-Extra: dev
Requires-Dist: pytest>=7.0.0; extra == "dev"
Requires-Dist: black>=23.0.0; extra == "dev"
Requires-Dist: flake8>=6.0.0; extra == "dev"
Dynamic: author
Dynamic: home-page
Dynamic: license-file
Dynamic: requires-python
